odm_hlp_oracle/__init__.py
odm_hlp_oracle-1.0.0.dist-info/licenses/LICENSE
odm_hlp_oracle-1.0.0.dist-info/METADATA
odm_hlp_oracle-1.0.0.dist-info/WHEEL
odm_hlp_oracle-1.0.0.dist-info/RECORD
